LICENSE
README.md
setup.py
armaan/__init__.py
armaan.egg-info/PKG-INFO
armaan.egg-info/SOURCES.txt
armaan.egg-info/dependency_links.txt
armaan.egg-info/requires.txt
armaan.egg-info/top_level.txt