Metadata-Version: 2.1
Name: armaan
Version: 3.20
Summary: Topsis Calculation
Home-page: https://github.com/armaanbhardwaj23
Author: Armaan Bhardwaj
Author-email: armaanbhardwaj23@gmail.com
License: MIT
Keywords: Topsis,TopsisPackage
Platform: UNKNOWN
Classifier: Development Status :: 3 - Alpha
Classifier: Intended Audience :: Developers
Classifier: License :: OSI Approved :: MIT License
Classifier: Programming Language :: Python :: 3
Classifier: Programming Language :: Python :: 3.4
Classifier: Programming Language :: Python :: 3.5
Classifier: Programming Language :: Python :: 3.6
License-File: LICENSE
